mockagent/__init__.py
mockagent-0.1.0.dist-info/licenses/LICENSE
mockagent-0.1.0.dist-info/METADATA
mockagent-0.1.0.dist-info/WHEEL
mockagent-0.1.0.dist-info/top_level.txt
mockagent-0.1.0.dist-info/RECORD
